{    "title": {
        "text": "不同經濟體的外來直接投資流量",
         "textStyle":{
        "color": "#FFFFFF",
        "bottom": 30
    }
    },
    "textStyle":{
        "color": "#FFFFFF"
    },
    "subtextStyle":{
        "color": "#FFFFFF"
    },
    "tooltip":{
        "trigger": "axis"
    },
     "legend": {
        "data":["中國","香港","台灣","德國","新加坡","美國"],
        "top": 30,
         "textStyle":{
        "color": "#FFFFFF"}
    },

    "toolbox": {
        "feature": {
            "saveAsImage": {}
        }
    },
    "grid": {
        "left": "3%",
        "right": "4%",
        "bottom": "3%",
        "containLabel": true
    },
    "xAxis" : [
        {
            "type" : "category",
            "boundaryGap" : false,
            "data" : ["2000","2001","2005","2010","2011","2012","2013","2014"]
        }
    ],
    "yAxis" : [
        {
            "type" : "value"
        }
    ],
    "series" : [
        {
            "name":"中國",
            "type":"line",
            "data":[40715,46878,72406,114734,123985,121080,123911,128500]
        },
        {
            "name":"香港",
            "type":"line",
            "data":[54582,29061,34058,70541,96581,70180,74294,103254]
        },
        {
            "name":"台灣",
            "type":"line",
            "data":[4928,4109,1625,2492,-1957,3207,3598,2839]
        },
        {
            "name":"德國",
            "type":"line",
            "data":[198276,26402,47449,65642,67515,20316,18193,1831]
        },
        {
            "name":"新加坡",
            "type":"line",
            "data":[15515,17007,18090,55076,48002,56659,64793,67523]
        },
        {
            "name":"美國",
            "type":"line",
            "data":[314007,159461,104773,198049,229862,169680,230768,92397]
        }]}